fivpy/__init__.py
fivpy/data/__init__.py
fivpy/data/data_1.csv
fivpy/data/data_2.csv
fivpy/data/data_3.csv
fivpy/datasets.py
fivpy/fivpy.py
fivpy/srs.py
fivpy-0.1.6.dist-info/LICENSE
fivpy-0.1.6.dist-info/WHEEL
fivpy-0.1.6.dist-info/METADATA
fivpy-0.1.6.dist-info/RECORD
