Metadata-Version: 2.1
Name: fivpy
Version: 0.1.6
Summary: A package for calculating forest inventories in python.
License: MIT
Author: Theilon Macedo
Requires-Python: >=3.9,<3.11
Classifier: License :: OSI Approved :: MIT License
Classifier: Programming Language :: Python :: 3
Classifier: Programming Language :: Python :: 3.10
Classifier: Programming Language :: Python :: 3.9
Requires-Dist: pandas (>=1.3.5,<2.0.0)
Requires-Dist: scipy (>=1.7.3,<2.0.0)
